README.md
setup.py
django_raise_exception_view.egg-info/PKG-INFO
django_raise_exception_view.egg-info/SOURCES.txt
django_raise_exception_view.egg-info/dependency_links.txt
django_raise_exception_view.egg-info/top_level.txt
raiseexception/__init__.py
raiseexception/models.py
raiseexception/tests.py
raiseexception/urls.py
raiseexception/views.py
raiseexception/__pycache__/__init__.cpython-37.pyc
raiseexception/__pycache__/models.cpython-37.pyc
raiseexception/__pycache__/tests.cpython-37.pyc
raiseexception/__pycache__/urls.cpython-37.pyc
raiseexception/__pycache__/views.cpython-37.pyc