Metadata-Version: 1.0
Name: django-raise-exception-view
Version: 1.0.2
Summary: Django view that raises an exception so you can test your logging setup
Home-page: http://github.com/brightinteractive/django-raise-exception-view/
Author: Bright Interactive
Author-email: francis@bright-interactive.co.uk
License: BSD
Platform: UNKNOWN
